corrily_live_price/__init__.py
corrily_live_price/api_client.py
corrily_live_price/configuration.py
corrily_live_price/exceptions.py
corrily_live_price/model_utils.py
corrily_live_price/rest.py
corrily_live_price/api/__init__.py
corrily_live_price/api/default_api.py
corrily_live_price/apis/__init__.py
corrily_live_price/model/__init__.py
corrily_live_price/model/get_batch_request.py
corrily_live_price/model/get_price_request.py
corrily_live_price/model/price.py
corrily_live_price/model/product.py
corrily_live_price/model/products.py
corrily_live_price/model/products_products.py
corrily_live_price/model/products_products_product1.py
corrily_live_price/model/products_products_product2.py
corrily_live_price/model/set_success_request.py
corrily_live_price/model/set_success_response.py
corrily_live_price/models/__init__.py
corrily_live_price-0.0.5.dist-info/METADATA
corrily_live_price-0.0.5.dist-info/WHEEL
corrily_live_price-0.0.5.dist-info/top_level.txt
corrily_live_price-0.0.5.dist-info/RECORD
